odoo_module_writers_lib/__init__.py
odoo_module_writers_lib/api.py
odoo_module_writers_lib/dates.py
odoo_module_writers_lib/debug.py
odoo_module_writers_lib/domain.py
odoo_module_writers_lib/lowlevel.py
odoo_module_writers_lib/models.py
odoo_module_writers_lib/testing.py
odoo_module_writers_lib/util.py
odoo_module_writers_lib/webui.py
odoo_module_writers_lib-0.0.1.dist-info/METADATA
odoo_module_writers_lib-0.0.1.dist-info/WHEEL
odoo_module_writers_lib-0.0.1.dist-info/licenses/LICENSE
odoo_module_writers_lib-0.0.1.dist-info/RECORD
